usolitaire/__init__.py
usolitaire/app.py
usolitaire/card_render.py
usolitaire/game.py
usolitaire/textual_app.css
usolitaire/textual_ui.py
usolitaire-1.1.0.dist-info/LICENSE
usolitaire-1.1.0.dist-info/METADATA
usolitaire-1.1.0.dist-info/WHEEL
usolitaire-1.1.0.dist-info/entry_points.txt
usolitaire-1.1.0.dist-info/top_level.txt
usolitaire-1.1.0.dist-info/RECORD
