Metadata-Version: 2.1
Name: usolitaire
Version: 1.1.0
Summary: Solitaire in your terminal
Home-page: https://github.com/eliasdorneles/usolitaire
Author: Elias Dorneles
Author-email: eliasdorneles@gmail.com
License: MIT license
Keywords: usolitaire
Classifier: Development Status :: 2 - Pre-Alpha
Classifier: Intended Audience :: Developers
Classifier: License :: OSI Approved :: MIT License
Classifier: Natural Language :: English
Classifier: Programming Language :: Python :: 3
Classifier: Programming Language :: Python :: 3.7
Classifier: Programming Language :: Python :: 3.8
Classifier: Programming Language :: Python :: 3.9
Classifier: Programming Language :: Python :: 3.10
Classifier: Programming Language :: Python :: 3.11
License-File: LICENSE
Requires-Dist: textual
